benchmark_functions/__init__.py
benchmark_functions/benchmark_functions.py
benchmark_functions/functions_info_loader.py
benchmark_functions/optimum_finder.py
benchmark_functions/functions_info/ackley.json
benchmark_functions/functions_info/bc-1.json
benchmark_functions/functions_info/bc-2.json
benchmark_functions/functions_info/bc-35.json
benchmark_functions/functions_info/de_jong_3.json
benchmark_functions/functions_info/de_jong_5.json
benchmark_functions/functions_info/easom.json
benchmark_functions/functions_info/egg_holder.json
benchmark_functions/functions_info/goldstein_and_price.json
benchmark_functions/functions_info/griewank.json
benchmark_functions/functions_info/himmelblau.json
benchmark_functions/functions_info/hyperellipsoid.json
benchmark_functions/functions_info/hypersphere.json
benchmark_functions/functions_info/keane.json
benchmark_functions/functions_info/martin_and_gaddy.json
benchmark_functions/functions_info/mccormick.json
benchmark_functions/functions_info/michalewicz.json
benchmark_functions/functions_info/picheny_goldstein_and_price.json
benchmark_functions/functions_info/pits_and_holes.json
benchmark_functions/functions_info/rana.json
benchmark_functions/functions_info/rastrigin.json
benchmark_functions/functions_info/rosenbrock.json
benchmark_functions/functions_info/schaffer_2.json
benchmark_functions/functions_info/schwefel.json
benchmark_functions/functions_info/shekel.json
benchmark_functions/functions_info/styblinski_and_tang.json
benchmark_functions-1.1.4.dist-info/LICENSE
benchmark_functions-1.1.4.dist-info/METADATA
benchmark_functions-1.1.4.dist-info/WHEEL
benchmark_functions-1.1.4.dist-info/top_level.txt
benchmark_functions-1.1.4.dist-info/RECORD
