Metadata-Version: 2.1
Name: benchmark-functions
Version: 1.1.4
Summary: A benchmark functions collection written in Python 3, suited for assessing the performances of optimisation problems on deterministic functions.
Home-page: https://gitlab.com/luca.baronti/python_benchmark_functions
Download-URL: https://pypi.org/project/benchmark_functions/
Author: Luca Baronti
Author-email: lbaronti@gmail.com
License: GNUv3
Keywords: Optimisation,Optimization,Benchmark,Functions
Classifier: Development Status :: 4 - Beta
Classifier: Intended Audience :: Education
Classifier: Intended Audience :: Science/Research
Classifier: Topic :: Scientific/Engineering :: Mathematics
Classifier: License :: OSI Approved :: GNU General Public License v3 (GPLv3)
Classifier: Programming Language :: Python :: 3
License-File: LICENSE
Requires-Dist: numpy
Requires-Dist: packaging
